<annotation>
	<folder>Doors</folder>
	<filename>DOR_S2_5.jpg</filename>
	<path>D:\ProjectHons\workspace\training_demo\images\Doors\DOR_S2_5.jpg</path>
	<source>
		<database>Unknown</database>
	</source>
	<size>
		<width>2135</width>
		<height>2123</height>
		<depth>3</depth>
	</size>
	<segmented>0</segmented>
	<object>
		<name>door</name>
		<pose>Unspecified</pose>
		<truncated>1</truncated>
		<difficult>0</difficult>
		<bndbox>
			<xmin>318</xmin>
			<ymin>1</ymin>
			<xmax>1830</xmax>
			<ymax>1872</ymax>
		</bndbox>
	</object>
</annotation>
